twshtd/__init__.py
twshtd/bin/__init__.py
twshtd/bin/cli.py
twshtd/lib/__init__.py
twshtd/lib/config.py
twshtd/lib/git_ops.py
twshtd-1.1.1.dist-info/METADATA
twshtd-1.1.1.dist-info/WHEEL
twshtd-1.1.1.dist-info/entry_points.txt
twshtd-1.1.1.dist-info/top_level.txt
twshtd-1.1.1.dist-info/RECORD
