Metadata-Version: 2.4
Name: twshtd
Version: 1.1.1
Summary: Git repository synchronization tool
Author-email: sysid <sysid@gmx.de>
Requires-Python: >=3.12
Requires-Dist: typer>=0.15.1
Requires-Dist: rich>=13.0.0
Provides-Extra: rplc
Requires-Dist: rplc; extra == "rplc"
